{
  "$schema": "https://mintlify.com/docs.json",
  "name": "Plugdata",
  "theme": "mint",
  "colors": {
    "primary": "#ea8c36",
    "light": "#69a1be",
    "dark": "#f8f8f8"
  },
  "favicon": "https://media.brand.dev/ead8aa21-f207-4f76-90f2-88a0b1cf8cc8.png",
  "logo": {
    "light": "https://media.brand.dev/ead8aa21-f207-4f76-90f2-88a0b1cf8cc8.png",
    "dark": "https://media.brand.dev/ead8aa21-f207-4f76-90f2-88a0b1cf8cc8.png"
  },
  "navbar": {
    "primary": {
      "type": "github",
      "href": "https://github.com/plugdata-team/plugdata"
    }
  },
  "footer": {
    "socials": {
      "github": "https://github.com/plugdata-team/plugdata",
      "discord": "https://discord.gg/eT2RxdF9Nq"
    }
  },
  "navigation": {
    "tabs": [
      {
        "tab": "Documentation",
        "groups": [
          {
            "group": "Getting Started",
            "pages": [
              "introduction",
              "installation",
              "quickstart"
            ]
          },
          {
            "group": "Core Concepts",
            "pages": [
              "concepts/patching-basics",
              "concepts/objects-and-connections",
              "concepts/plugin-vs-standalone",
              "concepts/daw-integration"
            ]
          },
          {
            "group": "User Guide",
            "pages": [
              "guides/interface-overview",
              "guides/creating-patches",
              "guides/using-objects",
              "guides/automation-parameters",
              "guides/presets-and-settings",
              "guides/audio-routing"
            ]
          },
          {
            "group": "Objects Reference",
            "pages": [
              "objects/overview",
              "objects/plugdata-objects",
              "objects/else-library",
              "objects/cyclone-library",
              "objects/vanilla-objects"
            ]
          },
          {
            "group": "Advanced",
            "pages": [
              "advanced/building-from-source",
              "advanced/adding-externals",
              "advanced/lua-scripting",
              "advanced/gem-graphics",
              "advanced/performance-optimization"
            ]
          },
          {
            "group": "Resources",
            "pages": [
              "resources/troubleshooting",
              "resources/faq",
              "resources/community",
              "resources/contributing"
            ]
          }
        ]
      },
      {
        "tab": "API Reference",
        "groups": [
          {
            "group": "Plugin Objects",
            "pages": [
              "api/param",
              "api/playhead",
              "api/plugin-latency",
              "api/daw-storage"
            ]
          },
          {
            "group": "Core Classes",
            "pages": [
              "api/plugin-processor",
              "api/canvas",
              "api/pd-instance"
            ]
          }
        ]
      }
    ]
  }
}
